gitflow/__init__.py
gitflow/cli.py
gitflow/commands.py
gitflow/__pycache__/__init__.cpython-312.pyc
gitflow/__pycache__/cli.cpython-312.pyc
gitflow/__pycache__/commands.cpython-312.pyc
gitflow_cli-0.1.0.dist-info/licenses/LICENSE
gitflow_cli-0.1.0.dist-info/METADATA
gitflow_cli-0.1.0.dist-info/WHEEL
gitflow_cli-0.1.0.dist-info/entry_points.txt
gitflow_cli-0.1.0.dist-info/top_level.txt
gitflow_cli-0.1.0.dist-info/RECORD
