Metadata-Version: 2.4
Name: gitflow-cli
Version: 0.1.0
Summary: A simple and powerful GitHub CLI helper tool
Home-page: https://github.com/basilshaji/gitflow
Author: Basil Shaji
Author-email: Basil Shaji <your.email@example.com>
License: MIT
Classifier: Programming Language :: Python :: 3
Classifier: License :: OSI Approved :: MIT License
Classifier: Operating System :: OS Independent
Requires-Python: >=3.6
Requires-Dist: colorama
Requires-Dist: inquirer
Dynamic: author
Dynamic: home-page
Dynamic: requires-python
